ImportarSurvey/ArcGISPythonApiDataAccess.py
ImportarSurvey/ArcGISRestApiDataAccess.py
ImportarSurvey/ArcpyDataAccess.py
ImportarSurvey/DataAccess.py
ImportarSurvey/Estadisticas.py
ImportarSurvey/Herramientas.py
ImportarSurvey/ImportarDatos.py
ImportarSurvey/ImportarDatosInyeccion.py
ImportarSurvey/ImportarDatosPrecarga.py
ImportarSurvey/InyectarEncuestas.py
ImportarSurvey/PrecargarEncuestas.py
ImportarSurvey/ProcesarEncuestas.py
ImportarSurvey/Utiles.py
ImportarSurvey/Widgets.py
ImportarSurvey/__init__.py
ImportarSurvey/_inyeccion.json
ImportarSurvey/_inyeccion_geo.json
ImportarSurvey/_inyeccion_geo_interesados.json
ImportarSurvey/_precarga.json
ImportarSurvey/_precarga_geo.json
ImportarSurvey/createtoolboxsupportfiles.py
ImportarSurvey/esri/arcpy/ImportarEncuestasActualizacion.py
ImportarSurvey/esri/help/gp/HerramientaInyectarEncuestas_ImportarEncuestasActualizacion.xml
ImportarSurvey/esri/help/gp/HerramientaPrecargarEncuestas_ImportarEncuestasActualizacion.xml
ImportarSurvey/esri/help/gp/ImportarEncuestasActualizacion_toolbox.xml
ImportarSurvey/esri/help/gp/toolboxes/ImportarEncuestasActualizacion.xml
ImportarSurvey/esri/toolboxes/ImportarEncuestasActualizacion.HerramientaInyectarEncuestas.pyt.xml
ImportarSurvey/esri/toolboxes/ImportarEncuestasActualizacion.HerramientaPrecargarEncuestas.pyt.xml
ImportarSurvey/esri/toolboxes/ImportarEncuestasActualizacion.pyt
ImportarSurvey/esri/toolboxes/ImportarEncuestasActualizacion.pyt.xml
ImportarSurvey-1.5.0.1.dist-info/LICENSE
ImportarSurvey-1.5.0.1.dist-info/METADATA
ImportarSurvey-1.5.0.1.dist-info/WHEEL
ImportarSurvey-1.5.0.1.dist-info/top_level.txt
ImportarSurvey-1.5.0.1.dist-info/RECORD
